RiftPackage/__init__.py
RiftPackage-0.0.7.dist-info/LICENSE
RiftPackage-0.0.7.dist-info/METADATA
RiftPackage-0.0.7.dist-info/WHEEL
RiftPackage-0.0.7.dist-info/entry_points.txt
RiftPackage-0.0.7.dist-info/top_level.txt
RiftPackage-0.0.7.dist-info/RECORD
