Metadata-Version: 2.1
Name: RiftPackage
Version: 0.0.7
Summary: Package For Rift
Home-page: UNKNOWN
Author: mxntyyy
Author-email: dankk1942@gmail.com
License: MIT
Platform: UNKNOWN
Classifier: License :: OSI Approved :: MIT License
Classifier: Programming Language :: Python :: 3
Classifier: Programming Language :: Python :: 3.7
Requires-Dist: requests
